{
  "url": "https://github.com/amilner42",
  "img": "https://avatars1.githubusercontent.com/u/9031171?v=3&s=460",
  "uid": 9031171,
  "repos": 40,
  "stars": 190,
  "followers": 27,
  "following": 22,
  "pinned": [
    {
      "url": "/amilner42/kleen"
    },
    {
      "url": "/amilner42/less-money-more-happy"
    },
    {
      "url": "/amilner42/meen-kickstarter"
    },
    {
      "url": "/amilner42/mea2n-kickstarter"
    },
    {
      "url": "/amilner42/interview-practice"
    },
    {
      "url": "/ubcio/web-app"
    }
  ],
  "worksfor": "Code Tidbit",
  "location": "Vancouver, BC, Canada",
  "fullname": "Arie Milner",
  "website": "",
  "avatar": "https://avatars1.githubusercontent.com/u/9031171?v=3&s=460",
  "contribs": 1301,
  "orgs": [
    {
      "ubcio": "https://avatars0.githubusercontent.com/u/16113443?v=3&s=70"
    },
    {
      "RippedGenes": "https://avatars3.githubusercontent.com/u/17804910?v=3&s=70"
    }
  ]
}