{
  "url": "https://github.com/babakness",
  "img": "https://avatars1.githubusercontent.com/u/2024235?v=3&s=460",
  "uid": 2024235,
  "repos": 19,
  "stars": 237,
  "followers": 2,
  "following": 2,
  "pinned": [
    {
      "url": "/babakness/AnchorTrigger"
    },
    {
      "url": "/babakness/Pipe"
    },
    {
      "url": "/babakness/meteor-opal"
    },
    {
      "url": "/babakness/BootstrapFormHelpers"
    },
    {
      "url": "/babakness/meteor-ionic"
    },
    {
      "url": "/babakness/quicktest"
    }
  ],
  "worksfor": "",
  "location": "",
  "fullname": "Babak",
  "website": "",
  "avatar": "https://avatars1.githubusercontent.com/u/2024235?v=3&s=460",
  "contribs": 124,
  "orgs": []
}