{
  "url": "https://github.com/blackcow02",
  "img": "https://avatars2.githubusercontent.com/u/4237136?v=3&s=460",
  "uid": 4237136,
  "repos": 29,
  "stars": 79,
  "followers": 2,
  "following": 27,
  "pinned": [
    {
      "url": "/blackcow02/EventStore"
    },
    {
      "url": "/blackcow02/EasyNetQ"
    },
    {
      "url": "/blackcow02/m-r"
    },
    {
      "url": "/blackcow02/Fohjin"
    },
    {
      "url": "/blackcow02/code"
    },
    {
      "url": "/blackcow02/gotraining"
    }
  ],
  "worksfor": "",
  "location": "",
  "fullname": "",
  "website": "",
  "avatar": "https://avatars2.githubusercontent.com/u/4237136?v=3&s=460",
  "contribs": 21,
  "orgs": []
}