{
  "url": "https://github.com/bradennapier",
  "img": "https://avatars2.githubusercontent.com/u/15365418?v=3&s=460",
  "uid": 15365418,
  "repos": 3,
  "stars": 990,
  "followers": 5,
  "following": 3,
  "pinned": [
    {
      "url": "/Dash-OS/redux-saga-process"
    },
    {
      "url": "/Dash-OS/tcl-modules"
    },
    {
      "url": "/Dash-OS/tcl-task-manager"
    },
    {
      "url": "/Dash-OS/cluster-comm"
    }
  ],
  "worksfor": "@Dash-OS",
  "location": "Los Angeles, CA",
  "fullname": "Braden Napier",
  "website": "",
  "avatar": "https://avatars2.githubusercontent.com/u/15365418?v=3&s=460",
  "contribs": 565,
  "orgs": [
    {
      "Dash-OS": "https://avatars1.githubusercontent.com/u/15355271?v=3&s=70"
    }
  ]
}