{
  "url": "https://github.com/cbebry",
  "img": "https://avatars0.githubusercontent.com/u/3312895?v=3&s=460",
  "uid": 3312895,
  "repos": 31,
  "stars": 800,
  "followers": 27,
  "following": 35,
  "pinned": [
    {
      "url": "/spectrumbranch/faire"
    },
    {
      "url": "/spectrumbranch/scurvy"
    },
    {
      "url": "/spectrumbranch/happybox"
    },
    {
      "url": "/spectrumbranch/mcd"
    },
    {
      "url": "/cbebry/gearsvge"
    },
    {
      "url": "/cbebry/sequelize"
    }
  ],
  "worksfor": "",
  "location": "",
  "fullname": "Christopher Bebry",
  "website": "",
  "avatar": "https://avatars0.githubusercontent.com/u/3312895?v=3&s=460",
  "contribs": 51,
  "orgs": [
    {
      "spectrumbranch": "https://avatars0.githubusercontent.com/u/739929?v=3&s=70"
    }
  ]
}