{
  "url": "https://github.com/CoSNaYe",
  "img": "https://avatars3.githubusercontent.com/u/11452327?v=3&s=460",
  "uid": 11452327,
  "repos": 22,
  "stars": 37,
  "followers": 2,
  "following": 1,
  "pinned": [
    {
      "url": "/CoSNaYe/ALPHACAMP_info"
    },
    {
      "url": "/CoSNaYe/W4D2_-ScrollView"
    },
    {
      "url": "/CoSNaYe/W4D2_PageView"
    },
    {
      "url": "/CoSNaYe/W4D3_category"
    },
    {
      "url": "/CoSNaYe/AC_W4D2H2_custom-view"
    },
    {
      "url": "/CoSNaYe/W5D2H1_collectionView"
    }
  ],
  "worksfor": "",
  "location": "",
  "fullname": "Ian Chen",
  "website": "",
  "avatar": "https://avatars3.githubusercontent.com/u/11452327?v=3&s=460",
  "contribs": 6,
  "orgs": []
}