{
  "url": "https://github.com/davidsonsns",
  "img": "https://avatars3.githubusercontent.com/u/9276511?v=3&s=460",
  "uid": 9276511,
  "repos": 32,
  "stars": 41,
  "followers": 20,
  "following": 3,
  "pinned": [
    {
      "url": "/davidsonsns/be-mean-instagram-mongodb-excercises"
    },
    {
      "url": "/davidsonsns/be-mean-instagram-artigos"
    },
    {
      "url": "/davidsonsns/workspace"
    },
    {
      "url": "/davidsonsns/be-mean-instagram"
    },
    {
      "url": "/davidsonsns/guia-frontend"
    },
    {
      "url": "/davidsonsns/markup"
    }
  ],
  "worksfor": "",
  "location": "",
  "fullname": "Davidson Nascimento",
  "website": "",
  "avatar": "https://avatars3.githubusercontent.com/u/9276511?v=3&s=460",
  "contribs": 23,
  "orgs": []
}