{
  "url": "https://github.com/DawnPaladin",
  "img": "https://avatars2.githubusercontent.com/u/5524469?v=3&s=460",
  "uid": 5524469,
  "repos": 29,
  "stars": 63,
  "followers": 16,
  "following": 8,
  "pinned": [
    {
      "url": "/DawnPaladin/periodic"
    },
    {
      "url": "/DawnPaladin/gial-degree-planner"
    },
    {
      "url": "/luke-schleicher/congress-tracker"
    },
    {
      "url": "/DawnPaladin/Family-Learning-Cycle"
    },
    {
      "url": "/DawnPaladin/danebook"
    },
    {
      "url": "/DawnPaladin/handbook"
    }
  ],
  "worksfor": "",
  "location": "Dallas, Texas",
  "fullname": "James Harris",
  "website": "http://jamesharris.design",
  "avatar": "https://avatars2.githubusercontent.com/u/5524469?v=3&s=460",
  "contribs": 671,
  "orgs": []
}