{
  "url": "https://github.com/Felk",
  "img": "https://avatars1.githubusercontent.com/u/1996138?v=3&s=460",
  "uid": 1996138,
  "repos": 23,
  "stars": 15,
  "followers": 8,
  "following": 17,
  "pinned": [
    {
      "url": "/Felk/Game-9"
    },
    {
      "url": "/Felk/MCCompiler"
    },
    {
      "url": "/Felk/ScrollsShop"
    },
    {
      "url": "/Felk/OCS-Server"
    },
    {
      "url": "/Felk/OCS-Client"
    },
    {
      "url": "/Felk/OCS-Launcher"
    }
  ],
  "worksfor": "",
  "location": "Germany",
  "fullname": "Felix König",
  "website": "http://fe1k.de",
  "avatar": "https://avatars1.githubusercontent.com/u/1996138?v=3&s=460",
  "contribs": 1278,
  "orgs": []
}