{
  "url": "https://github.com/fpradah",
  "img": "https://avatars1.githubusercontent.com/u/13364959?v=3&s=460",
  "uid": 13364959,
  "repos": 9,
  "stars": 6,
  "followers": 6,
  "following": 7,
  "pinned": [
    {
      "url": "/fpradah/busing"
    },
    {
      "url": "/fpradah/change_data_structure"
    },
    {
      "url": "/fpradah/genetic_ab_problem"
    },
    {
      "url": "/fpradah/hash-code-2016"
    },
    {
      "url": "/fpradah/LearningGitHub"
    },
    {
      "url": "/fpradah/tales"
    }
  ],
  "worksfor": "",
  "location": "",
  "fullname": "Fernando Prada",
  "website": "",
  "avatar": "https://avatars1.githubusercontent.com/u/13364959?v=3&s=460",
  "contribs": 6,
  "orgs": []
}