{
  "url": "https://github.com/giscafer",
  "img": "https://avatars0.githubusercontent.com/u/8676711?v=3&s=460",
  "uid": 8676711,
  "repos": 53,
  "stars": 743,
  "followers": 175,
  "following": 82,
  "pinned": [
    {
      "url": "/giscafer/Ponitor"
    },
    {
      "url": "/giscafer/FinalScheduler"
    },
    {
      "url": "/giscafer/hexo-theme-cafe"
    },
    {
      "url": "/giscafer/wechat-weapp-mapdemo"
    },
    {
      "url": "/giscafer/front-end-manual"
    },
    {
      "url": "/giscafer/project"
    }
  ],
  "worksfor": "",
  "location": "GuangZhou China",
  "fullname": "Nickbing Lao",
  "website": "http://giscafer.com",
  "avatar": "https://avatars0.githubusercontent.com/u/8676711?v=3&s=460",
  "contribs": 985,
  "orgs": [
    {
      "gis520": "https://avatars2.githubusercontent.com/u/17235971?v=3&s=70"
    },
    {
      "viseye": "https://avatars1.githubusercontent.com/u/21366573?v=3&s=70"
    }
  ]
}