{
  "url": "https://github.com/hhff",
  "img": "https://avatars2.githubusercontent.com/u/2865404?v=3&s=460",
  "uid": 2865404,
  "repos": 67,
  "stars": 455,
  "followers": 51,
  "following": 40,
  "pinned": [
    {
      "url": "/hhff/ember-infinity"
    },
    {
      "url": "/hhff/spree-ember"
    },
    {
      "url": "/hhff/spree_ams"
    },
    {
      "url": "/hhff/SpacegrayEighties.vim"
    },
    {
      "url": "/hhff/ember-chimp"
    },
    {
      "url": "/hhff/reaction"
    }
  ],
  "worksfor": "Sanctuary Computer, Inc",
  "location": "NYC",
  "fullname": "Hugh Francis",
  "website": "http://sanctuary.computer",
  "avatar": "https://avatars2.githubusercontent.com/u/2865404?v=3&s=460",
  "contribs": 609,
  "orgs": [
    {
      "spree": "https://avatars3.githubusercontent.com/u/56702?v=3&s=70"
    },
    {
      "sanctuarycomputer": "https://avatars2.githubusercontent.com/u/10889595?v=3&s=70"
    },
    {
      "herdup": "https://avatars0.githubusercontent.com/u/11083118?v=3&s=70"
    },
    {
      "pickpeteee": "https://avatars0.githubusercontent.com/u/21177624?v=3&s=70"
    }
  ]
}