{
  "url": "https://github.com/irobayna",
  "img": "https://avatars1.githubusercontent.com/u/349175?v=3&s=460",
  "uid": 349175,
  "repos": 37,
  "stars": 1100,
  "followers": 18,
  "following": 56,
  "pinned": [
    {
      "url": "/nuxt/nuxt.js"
    },
    {
      "url": "/DevExpress/testcafe"
    },
    {
      "url": "/lynndylanhurley/ng-token-auth"
    },
    {
      "url": "/kputnam/stupidedi"
    },
    {
      "url": "/fandogh/nuxt-helpers"
    },
    {
      "url": "/irobayna/puma"
    }
  ],
  "worksfor": "",
  "location": "Melbourne, FL",
  "fullname": "Isi Robayna",
  "website": "https://twitter.com/irobayna",
  "avatar": "https://avatars1.githubusercontent.com/u/349175?v=3&s=460",
  "contribs": 33,
  "orgs": []
}