{
  "url": "https://github.com/lbarker",
  "img": "https://avatars0.githubusercontent.com/u/1869546?v=3&s=460",
  "uid": 1869546,
  "repos": 17,
  "stars": 25,
  "followers": 3,
  "following": 3,
  "pinned": [
    {
      "url": "/lbarker/cp2012"
    },
    {
      "url": "/lbarker/weblbdesigns.dev"
    },
    {
      "url": "/lbarker/xyz_framework_commit_history"
    },
    {
      "url": "/lbarker/xyztextbooks_webroot_commit_history"
    },
    {
      "url": "/lbarker/mathtv_database_layer_commit_history"
    },
    {
      "url": "/lbarker/fun-portfolio-template"
    }
  ],
  "worksfor": "Cal Poly Corporation",
  "location": "San Luis Obispo",
  "fullname": "Lauren Barker",
  "website": "http://lbarker.github.io/",
  "avatar": "https://avatars0.githubusercontent.com/u/1869546?v=3&s=460",
  "contribs": 5,
  "orgs": []
}