{
  "url": "https://github.com/lwzjf",
  "img": "https://avatars1.githubusercontent.com/u/6193059?v=3&s=460",
  "uid": 6193059,
  "repos": 50,
  "stars": 19,
  "followers": 0,
  "following": 9,
  "pinned": [
    {
      "url": "/lwzjf/MemoEveryDay"
    },
    {
      "url": "/lwzjf/generator-ng-fullstack"
    },
    {
      "url": "/lwzjf/spring-demo"
    },
    {
      "url": "/lwzjf/RubyDemo"
    },
    {
      "url": "/lwzjf/first_app"
    },
    {
      "url": "/lwzjf/dotfiles"
    }
  ],
  "worksfor": "",
  "location": "",
  "fullname": "",
  "website": "",
  "avatar": "https://avatars1.githubusercontent.com/u/6193059?v=3&s=460",
  "contribs": 25,
  "orgs": []
}