{
  "url": "https://github.com/marcioadr88",
  "img": "https://avatars0.githubusercontent.com/u/746815?v=3&s=460",
  "uid": 746815,
  "repos": 1,
  "stars": 755,
  "followers": 23,
  "following": 33,
  "pinned": [
    {
      "url": "/marcioadr88/weka-datasource-extension"
    }
  ],
  "worksfor": "Telecom Personal Paraguay",
  "location": "Asunción, Paraguay",
  "fullname": "Marcio Duarte",
  "website": "",
  "avatar": "https://avatars0.githubusercontent.com/u/746815?v=3&s=460",
  "contribs": 0,
  "orgs": []
}