{
  "url": "https://github.com/martinmurciego",
  "img": "https://avatars1.githubusercontent.com/u/7759127?v=3&s=460",
  "uid": 7759127,
  "repos": 91,
  "stars": 342,
  "followers": 3,
  "following": 9,
  "pinned": [
    {
      "url": "/martinmurciego/DRIVER-BACKUP-WINDOWS"
    },
    {
      "url": "/martinmurciego/criadero-xp"
    },
    {
      "url": "/martinmurciego/sails-angular-yeoman-logindemo"
    },
    {
      "url": "/martinmurciego/sailsjs-v10-angularjs-requirejs-boilerplate"
    },
    {
      "url": "/martinmurciego/sistemaodontologia"
    },
    {
      "url": "/martinmurciego/nodebeginner.org"
    }
  ],
  "worksfor": "",
  "location": "",
  "fullname": "Martin Murciego",
  "website": "",
  "avatar": "https://avatars1.githubusercontent.com/u/7759127?v=3&s=460",
  "contribs": 13,
  "orgs": []
}