{
  "url": "https://github.com/patw0929",
  "img": "https://avatars3.githubusercontent.com/u/3055294?v=3&s=460",
  "uid": 3055294,
  "repos": 74,
  "stars": 397,
  "followers": 32,
  "following": 16,
  "pinned": [
    {
      "url": "/patw0929/react-intl-tel-input"
    },
    {
      "url": "/patw0929/react-redux-guestbook-practice"
    },
    {
      "url": "/patw0929/react-smartbanner"
    },
    {
      "url": "/patw0929/react-twzipcode"
    },
    {
      "url": "/patw0929/github-repo-finder"
    },
    {
      "url": "/f2etw/detect-inapp"
    }
  ],
  "worksfor": "",
  "location": "Taipei, Taiwan",
  "fullname": "Patrick Wang",
  "website": "https://patw.me",
  "avatar": "https://avatars3.githubusercontent.com/u/3055294?v=3&s=460",
  "contribs": 1007,
  "orgs": [],
  "developerprogram": true
}