{
  "url": "https://github.com/PrabhanshuAttri",
  "img": "https://avatars1.githubusercontent.com/u/4739486?v=3&s=460",
  "uid": 4739486,
  "repos": 79,
  "stars": 123,
  "followers": 22,
  "following": 54,
  "pinned": [
    {
      "url": "/google/physical-web"
    },
    {
      "url": "/google/eddystone"
    },
    {
      "url": "/WomenWhoCode/guidelines-resources"
    },
    {
      "url": "/nirmankarta/PyBeacon"
    },
    {
      "url": "/PrabhanshuAttri/PyFy"
    },
    {
      "url": "/una/CSSgram"
    }
  ],
  "worksfor": "@nirmankarta @forksociety",
  "location": "India",
  "fullname": "Prabhanshu Attri",
  "website": "http://prabhanshu.com",
  "avatar": "https://avatars1.githubusercontent.com/u/4739486?v=3&s=460",
  "contribs": 1884,
  "orgs": [
    {
      "Zomato": "https://avatars2.githubusercontent.com/u/1112143?v=3&s=70"
    },
    {
      "fossasia": "https://avatars1.githubusercontent.com/u/6295529?v=3&s=70"
    },
    {
      "nirmankarta": "https://avatars3.githubusercontent.com/u/9516701?v=3&s=70"
    },
    {
      "forksociety": "https://avatars2.githubusercontent.com/u/21275911?v=3&s=70"
    }
  ],
  "developerprogram": true
}