{
  "url": "https://github.com/quentunahelper",
  "img": "https://avatars0.githubusercontent.com/u/3633246?v=3&s=460",
  "uid": 3633246,
  "repos": 13,
  "stars": 169,
  "followers": 5,
  "following": 3,
  "pinned": [
    {
      "url": "/quentunahelper/todo-cli"
    },
    {
      "url": "/quentunahelper/select-a-from-grade"
    },
    {
      "url": "/quentunahelper/game-theoretic-feedback-loop"
    },
    {
      "url": "/quentunahelper/forensoid"
    },
    {
      "url": "/quentunahelper/penn-state-auto-register"
    },
    {
      "url": "/quentunahelper/biesinger"
    }
  ],
  "worksfor": "",
  "location": "State College, PA",
  "fullname": "Quentin Topper",
  "website": "",
  "avatar": "https://avatars0.githubusercontent.com/u/3633246?v=3&s=460",
  "contribs": 3,
  "orgs": []
}