{
  "url": "https://github.com/RabeaGleissner",
  "img": "https://avatars1.githubusercontent.com/u/8995723?v=3&s=460",
  "uid": 8995723,
  "repos": 47,
  "stars": 11,
  "followers": 31,
  "following": 34,
  "pinned": [
    {
      "url": "/RabeaGleissner/RabeaGleissner.github.io"
    },
    {
      "url": "/RabeaGleissner/second-http-server"
    },
    {
      "url": "/RabeaGleissner/java-tic-tac-toe"
    },
    {
      "url": "/RabeaGleissner/elixir_tic_tac_toe"
    },
    {
      "url": "/RabeaGleissner/london"
    }
  ],
  "worksfor": "",
  "location": "London",
  "fullname": "Rabea Gleissner",
  "website": "http://rabea.co.uk",
  "avatar": "https://avatars1.githubusercontent.com/u/8995723?v=3&s=460",
  "contribs": 579,
  "orgs": []
}