{
  "url": "https://github.com/Seabsaye",
  "img": "https://avatars0.githubusercontent.com/u/12981112?v=3&s=460",
  "uid": 12981112,
  "repos": 10,
  "stars": 84,
  "followers": 15,
  "following": 27,
  "pinned": [
    {
      "url": "/Seabsaye/Cpp-Projects"
    },
    {
      "url": "/Seabsaye/Python-Projects"
    },
    {
      "url": "/Seabsaye/Seabsaye.github.io"
    },
    {
      "url": "/Seabsaye/iOS-Project-Alfred"
    },
    {
      "url": "/Seabsaye/engHacks"
    },
    {
      "url": "/Seabsaye/React-Fundamentals"
    }
  ],
  "worksfor": "",
  "location": "Ontario",
  "fullname": "Sebastian Kolosa",
  "website": "http://sebastiankolosa.com",
  "avatar": "https://avatars0.githubusercontent.com/u/12981112?v=3&s=460",
  "contribs": 281,
  "orgs": []
}