{
  "url": "https://github.com/simomarsili",
  "img": "https://avatars0.githubusercontent.com/u/14930642?v=3&s=460",
  "uid": 14930642,
  "repos": 6,
  "stars": 96,
  "followers": 2,
  "following": 2,
  "pinned": [
    {
      "url": "/simomarsili/elss"
    },
    {
      "url": "/simomarsili/ndd"
    },
    {
      "url": "/simomarsili/z-scores"
    },
    {
      "url": "/simomarsili/scikit-learn"
    },
    {
      "url": "/simomarsili/mpl"
    },
    {
      "url": "/simomarsili/fmpl"
    }
  ],
  "worksfor": "",
  "location": "",
  "fullname": "Simone Marsili",
  "website": "",
  "avatar": "https://avatars0.githubusercontent.com/u/14930642?v=3&s=460",
  "contribs": 247,
  "orgs": []
}