{
  "url": "https://github.com/SmoothHacker",
  "img": "https://avatars1.githubusercontent.com/u/16490754?v=3&s=460",
  "uid": 16490754,
  "repos": 5,
  "stars": 150,
  "followers": 4,
  "following": 17,
  "pinned": [
    {
      "url": "/SmoothHacker/PatientManager"
    },
    {
      "url": "/SmoothHacker/HotelReservationSystem"
    },
    {
      "url": "/SmoothHacker/BankingSoftware"
    },
    {
      "url": "/SmoothHacker/SmoothHacker.github.io"
    }
  ],
  "worksfor": "",
  "location": "Chicago, Illinois",
  "fullname": "Scott Lagler",
  "website": "",
  "avatar": "https://avatars1.githubusercontent.com/u/16490754?v=3&s=460",
  "contribs": 77,
  "orgs": []
}