{
  "url": "https://github.com/sora4",
  "img": "https://avatars1.githubusercontent.com/u/1404721?v=3&s=460",
  "uid": 1404721,
  "repos": 9,
  "stars": 91,
  "followers": 0,
  "following": 1,
  "pinned": [
    {
      "url": "/sora4/cheesesquare"
    },
    {
      "url": "/sora4/Semantic-UI"
    },
    {
      "url": "/sora4/node-fluent-ffmpeg"
    },
    {
      "url": "/sora4/micropython-esp32"
    },
    {
      "url": "/sora4/micropython-upybbot"
    },
    {
      "url": "/sora4/KNX"
    }
  ],
  "worksfor": "",
  "location": "",
  "fullname": "",
  "website": "",
  "avatar": "https://avatars1.githubusercontent.com/u/1404721?v=3&s=460",
  "contribs": 6,
  "orgs": []
}