{
  "url": "https://github.com/StevenTTuD",
  "img": "https://avatars0.githubusercontent.com/u/7014009?v=3&s=460",
  "uid": 7014009,
  "repos": 112,
  "stars": 508,
  "followers": 8,
  "following": 92,
  "pinned": [
    {
      "url": "/StevenTTuD/f2e-workflow-labs"
    },
    {
      "url": "/StevenTTuD/aws-whitepaper-downloader"
    },
    {
      "url": "/StevenTTuD/pygments-css"
    },
    {
      "url": "/StevenTTuD/gwt-bootstrap"
    },
    {
      "url": "/StevenTTuD/gwt2-mvn-bootstrap"
    },
    {
      "url": "/StevenTTuD/gwtbootstrap3"
    }
  ],
  "worksfor": "",
  "location": "",
  "fullname": "",
  "website": "",
  "avatar": "https://avatars0.githubusercontent.com/u/7014009?v=3&s=460",
  "contribs": 108,
  "orgs": []
}