{
  "url": "https://github.com/theangi",
  "img": "https://avatars1.githubusercontent.com/u/3329414?v=3&s=460",
  "uid": 3329414,
  "repos": 6,
  "stars": 53,
  "followers": 1,
  "following": 2,
  "pinned": [
    {
      "url": "/theangi/SDEM"
    },
    {
      "url": "/theangi/P2PRMI"
    },
    {
      "url": "/theangi/android-swipe-to-dismiss-undo"
    },
    {
      "url": "/theangi/IAMDinosaur"
    },
    {
      "url": "/theangi/Marlin"
    },
    {
      "url": "/theangi/SublimeBaan"
    }
  ],
  "worksfor": "",
  "location": "Italy",
  "fullname": "Matteo Angiari",
  "website": "",
  "avatar": "https://avatars1.githubusercontent.com/u/3329414?v=3&s=460",
  "contribs": 123,
  "orgs": []
}