{
  "url": "https://github.com/thecoducer",
  "img": "https://avatars1.githubusercontent.com/u/24296902?v=3&s=460",
  "uid": 24296902,
  "repos": 5,
  "stars": 8,
  "followers": 5,
  "following": 8,
  "pinned": [
    {
      "url": "/thecoducer/thecoducer.github.io"
    },
    {
      "url": "/thecoducer/c_programs"
    },
    {
      "url": "/thecoducer/codelibrary"
    },
    {
      "url": "/thecoducer/free-programming-books"
    },
    {
      "url": "/thecoducer/python_programs"
    }
  ],
  "worksfor": "",
  "location": "",
  "fullname": "Mayukh Datta",
  "website": "https://thecoducer.tech.blog/",
  "avatar": "https://avatars1.githubusercontent.com/u/24296902?v=3&s=460",
  "contribs": 115,
  "orgs": []
}