{
  "url": "https://github.com/tuxcrafting",
  "img": "https://avatars1.githubusercontent.com/u/12471641?v=3&s=460",
  "uid": 12471641,
  "repos": 70,
  "stars": 794,
  "followers": 11,
  "following": 26,
  "pinned": [
    {
      "url": "/Neoscript-lang/neoscript"
    },
    {
      "url": "/tuxcrafting/straw"
    },
    {
      "url": "/logy-lang/logy"
    },
    {
      "url": "/tuxcrafting/y"
    },
    {
      "url": "/tuxcrafting/jlisp"
    }
  ],
  "worksfor": "VSL",
  "location": "Uranus (don't ask me how)",
  "fullname": "WcwPenguin",
  "website": "https://tuxcrafting.github.io/",
  "avatar": "https://avatars1.githubusercontent.com/u/12471641?v=3&s=460",
  "contribs": 429,
  "orgs": []
}