{
  "url": "https://github.com/VictorCoder123",
  "img": "https://avatars2.githubusercontent.com/u/3804486?v=3&s=460",
  "uid": 3804486,
  "repos": 24,
  "stars": 199,
  "followers": 15,
  "following": 36,
  "pinned": [
    {
      "url": "/VictorCoder123/ghost-storage"
    },
    {
      "url": "/VictorCoder123/shmup"
    },
    {
      "url": "/VictorCoder123/android-swarm"
    },
    {
      "url": "/VictorCoder123/sudoku"
    },
    {
      "url": "/VictorCoder123/500lines"
    },
    {
      "url": "/VictorCoder123/BidirAlgorithm"
    }
  ],
  "worksfor": "",
  "location": "Nashville",
  "fullname": "Qishen",
  "website": "",
  "avatar": "https://avatars2.githubusercontent.com/u/3804486?v=3&s=460",
  "contribs": 154,
  "orgs": [],
  "developerprogram": true
}