{
  "url": "https://github.com/vijayee",
  "img": "https://avatars3.githubusercontent.com/u/7297296?v=3&s=460",
  "uid": 7297296,
  "repos": 70,
  "stars": 199,
  "followers": 14,
  "following": 40,
  "pinned": [
    {
      "url": "/vijayee/cuckoo-filter"
    },
    {
      "url": "/vijayee/js-ipfs-example-browser"
    },
    {
      "url": "/vijayee/prometheus-website"
    },
    {
      "url": "/vijayee/tourguide"
    },
    {
      "url": "/vijayee/Account"
    },
    {
      "url": "/vijayee/udp-messages"
    }
  ],
  "worksfor": "Prometheus",
  "location": "@VijayeeKulkaa",
  "fullname": "Victor Morrow",
  "website": "http://prometheus.network",
  "avatar": "https://avatars3.githubusercontent.com/u/7297296?v=3&s=460",
  "contribs": 239,
  "orgs": [
    {
      "MocoMakers": "https://avatars1.githubusercontent.com/u/21271672?v=3&s=70"
    }
  ]
}