{
  "url": "https://github.com/wpcarro",
  "img": "https://avatars2.githubusercontent.com/u/13058701?v=3&s=460",
  "uid": 13058701,
  "repos": 59,
  "stars": 202,
  "followers": 29,
  "following": 62,
  "pinned": [
    {
      "url": "/wpcarro/pc_settings"
    },
    {
      "url": "/wpcarro/ramda-extensions"
    },
    {
      "url": "/wpcarro/context_coloring"
    },
    {
      "url": "/wpcarro/stop-writing-for-loops"
    },
    {
      "url": "/wpcarro/javascript-algorithms"
    },
    {
      "url": "/wpcarro/google-spreadsheet-javascript"
    }
  ],
  "worksfor": "",
  "location": "New York, New York",
  "fullname": "William Carroll",
  "website": "",
  "avatar": "https://avatars2.githubusercontent.com/u/13058701?v=3&s=460",
  "contribs": 970,
  "orgs": []
}