{
  "url": "https://github.com/wuworkshop",
  "img": "https://avatars0.githubusercontent.com/u/605787?v=3&s=460",
  "uid": 605787,
  "repos": 19,
  "stars": 644,
  "followers": 15,
  "following": 20,
  "pinned": [
    {
      "url": "/wuworkshop/LPTHW"
    },
    {
      "url": "/wuworkshop/try_git"
    },
    {
      "url": "/wuworkshop/omrails"
    },
    {
      "url": "/wuworkshop/hubbub"
    },
    {
      "url": "/wuworkshop/habitrpg"
    },
    {
      "url": "/wuworkshop/microscope-0.8.1.3"
    }
  ],
  "worksfor": "",
  "location": "NYC",
  "fullname": "",
  "website": "",
  "avatar": "https://avatars0.githubusercontent.com/u/605787?v=3&s=460",
  "contribs": 276,
  "orgs": []
}