{
  "url": "https://github.com/wxyudl",
  "img": "https://avatars3.githubusercontent.com/u/9672031?v=3&s=460",
  "uid": 9672031,
  "repos": 31,
  "stars": 58,
  "followers": 2,
  "following": 5,
  "pinned": [
    {
      "url": "/wxyudl/watson-advisor"
    },
    {
      "url": "/wxyudl/uTracker"
    },
    {
      "url": "/wxyudl/CSA-Monitor"
    },
    {
      "url": "/wxyudl/web_manual"
    },
    {
      "url": "/wxyudl/group"
    },
    {
      "url": "/wxyudl/oneKit"
    }
  ],
  "worksfor": "IBM",
  "location": "Dalian",
  "fullname": "小鱼果",
  "website": "http://www.xilinjie.com",
  "avatar": "https://avatars3.githubusercontent.com/u/9672031?v=3&s=460",
  "contribs": 124,
  "orgs": []
}