{
  "url": "https://github.com/zaplitny",
  "img": "https://avatars0.githubusercontent.com/u/756746?v=3&s=460",
  "uid": 756746,
  "repos": 18,
  "stars": 497,
  "followers": 6,
  "following": 1,
  "pinned": [
    {
      "url": "/zaplitny/timetrackio-i18n"
    },
    {
      "url": "/zaplitny/atimelogger-i18n"
    },
    {
      "url": "/zaplitny/atimelogger.github.io"
    },
    {
      "url": "/zaplitny/zaplitny.github.io"
    },
    {
      "url": "/zaplitny/iVersion"
    },
    {
      "url": "/zaplitny/ember-cli-bootstrap-modal-example"
    }
  ],
  "worksfor": "aLoggers",
  "location": "Minsk",
  "fullname": "Sergei Zaplitny",
  "website": "http://www.aloggers.com",
  "avatar": "https://avatars0.githubusercontent.com/u/756746?v=3&s=460",
  "contribs": 34,
  "orgs": []
}